tempEgo/RANSAC.py
tempEgo/__init__.py
tempEgo/calibration.py
tempEgo/data_unpacker.py
tempEgo/dataset_loaders.py
tempEgo/error_and_loss_function.py
tempEgo/external_dataset_import.py
tempEgo/least_squares.py
tempEgo/main.py
tempEgo-0.0.1.dist-info/LICENSE
tempEgo-0.0.1.dist-info/METADATA
tempEgo-0.0.1.dist-info/WHEEL
tempEgo-0.0.1.dist-info/top_level.txt
tempEgo-0.0.1.dist-info/RECORD
