Metadata-Version: 2.1
Name: tempEgo
Version: 0.0.1
Summary: A package for estimating ego-motion velocity using millimetre-wave (mmWave) radar.
Home-page: https://github.com/samuelLovett/tempEgo.git
Author: Samuel Lovett
Author-email: Samuel Lovett <samuellovett@cmail.carleton.ca>
Project-URL: Homepage, https://github.com/samuelLovett/tempEgo.git
Classifier: Programming Language :: Python :: 3
Classifier: License :: OSI Approved :: MIT License
Classifier: Operating System :: OS Independent
Requires-Python: >=3.10
License-File: LICENSE
Requires-Dist: numpy (>=1.23.1)
Requires-Dist: scipy (>=1.10.1)
